ensemble_md/__init__.py
ensemble_md/_version.py
ensemble_md/replica_exchange_EE.py
ensemble_md/analysis/analyze_free_energy.py
ensemble_md/analysis/analyze_matrix.py
ensemble_md/analysis/analyze_traj.py
ensemble_md/analysis/clustering.py
ensemble_md/analysis/msm_analysis.py
ensemble_md/cli/analyze_REXEE.py
ensemble_md/cli/explore_REXEE.py
ensemble_md/cli/run_REXEE.py
ensemble_md/data/README.md
ensemble_md/data/look_and_say.dat
ensemble_md/tests/__init__.py
ensemble_md/tests/test_analyze_free_energy.py
ensemble_md/tests/test_analyze_matrix.py
ensemble_md/tests/test_analyze_traj.py
ensemble_md/tests/test_clustering.py
ensemble_md/tests/test_gmx_parser.py
ensemble_md/tests/test_mpi_func.py
ensemble_md/tests/test_replica_exchange_EE.py
ensemble_md/tests/test_synthesize_data.py
ensemble_md/tests/test_utils.py
ensemble_md/tests/data/expanded.mdp
ensemble_md/tests/data/sys.gro
ensemble_md/tests/data/sys.top
ensemble_md/tests/data/dhdl/dhdl_0.xvg
ensemble_md/tests/data/dhdl/dhdl_1.xvg
ensemble_md/tests/data/dhdl/dhdl_2.xvg
ensemble_md/tests/data/dhdl/dhdl_3.xvg
ensemble_md/tests/data/log/EXE.log
ensemble_md/tests/data/log/EXE_0.log
ensemble_md/tests/data/log/EXE_1.log
ensemble_md/tests/data/log/EXE_2.log
ensemble_md/tests/data/log/EXE_3.log
ensemble_md/tests/data/log/HREX.log
ensemble_md/tests/data/log/case2_1.log
ensemble_md/tests/data/log/case2_2.log
ensemble_md/tests/data/log/case3.log
ensemble_md/tests/data/stitch_test/sim_0/iteration_0/dhdl.xvg
ensemble_md/tests/data/stitch_test/sim_0/iteration_0/dhdl_short.xvg
ensemble_md/tests/data/stitch_test/sim_0/iteration_1/dhdl.xvg
ensemble_md/tests/data/stitch_test/sim_0/iteration_1/dhdl_short.xvg
ensemble_md/tests/data/stitch_test/sim_1/iteration_0/dhdl.xvg
ensemble_md/tests/data/stitch_test/sim_1/iteration_0/dhdl_short.xvg
ensemble_md/tests/data/stitch_test/sim_1/iteration_1/dhdl.xvg
ensemble_md/tests/data/stitch_test/sim_1/iteration_1/dhdl_short.xvg
ensemble_md/utils/exceptions.py
ensemble_md/utils/gmx_parser.py
ensemble_md-1.0.0.dist-info/LICENSE
ensemble_md-1.0.0.dist-info/METADATA
ensemble_md-1.0.0.dist-info/WHEEL
ensemble_md-1.0.0.dist-info/entry_points.txt
ensemble_md-1.0.0.dist-info/top_level.txt
ensemble_md-1.0.0.dist-info/RECORD
